LICENSE.txt
MANIFEST.in
README.txt
build.txt
ez_setup.py
requirements.txt
setup.py
narc/__init__.py
narc/amqp.py
narc/configuration.py
narc/log.py
narc/main.py
narc/plugins/__init__.py
narc/plugins/email.py
narc/plugins/internal.py
narc/plugins/testrungroup.py
slickqa_narc.egg-info/PKG-INFO
slickqa_narc.egg-info/SOURCES.txt
slickqa_narc.egg-info/dependency_links.txt
slickqa_narc.egg-info/entry_points.txt
slickqa_narc.egg-info/requires.txt
slickqa_narc.egg-info/top_level.txt