Metadata-Version: 1.0
Name: slickqa-narc
Version: 1.0.18
Summary: A program responsible for responding to Slick events
Home-page: http://code.google.com/p/slickqa
Author: Slick Developers
Author-email: UNKNOWN
License: License :: OSI Approved :: Apache Software License
Platform: UNKNOWN
